nela_features/__init__.py
nela_features/nela_features.py
nela_features-3.0.1.dist-info/LICENSE
nela_features-3.0.1.dist-info/METADATA
nela_features-3.0.1.dist-info/WHEEL
nela_features-3.0.1.dist-info/top_level.txt
nela_features-3.0.1.dist-info/RECORD
